{
  "00000000000": {
    "nombre": "Admin",
    "apellido": "General",
    "email": "admin@provincia.gob.ar",
    "cue": [
      "1800000"
    ],
    "rol": "admin",
    "login": "00000000000"
  },
  "23236614484": {
    "nombre": "Cirino",
    "apellido": "Batlle",
    "email": "clementinabarrios@millan.es",
    "cue": [
      "1801380"
    ],
    "rol": "usuario",
    "login": "23236614484"
  },
  "23474554379": {
    "nombre": "Estefanía",
    "apellido": "Larrañaga",
    "email": "maria-belen91@hotmail.com",
    "cue": [
      "1801828"
    ],
    "rol": "usuario",
    "login": "23474554379"
  },
  "21550853863": {
    "nombre": "Amaro",
    "apellido": "Palacio",
    "email": "gertrudispalomares@gual.net",
    "cue": [
      "1803297"
    ],
    "rol": "usuario",
    "login": "21550853863"
  },
  "20736708182": {
    "nombre": "Fabiola",
    "apellido": "Robles",
    "email": "nataliatorrijos@millan-cuenca.es",
    "cue": [
      "1808193"
    ],
    "rol": "usuario",
    "login": "20736708182"
  },
  "24105060228": {
    "nombre": "Ileana",
    "apellido": "Carro",
    "email": "bustamanteadrian@yahoo.com",
    "cue": [
      "1803462"
    ],
    "rol": "usuario",
    "login": "24105060228"
  },
  "24563776539": {
    "nombre": "Ester",
    "apellido": "Escrivá",
    "email": "aureliobarbero@yahoo.com",
    "cue": [
      "1806360"
    ],
    "rol": "usuario",
    "login": "24563776539"
  },
  "25942958976": {
    "nombre": "Gaspar",
    "apellido": "Segarra",
    "email": "natalio41@hotmail.com",
    "cue": [
      "1802723"
    ],
    "rol": "usuario",
    "login": "25942958976"
  },
  "21270517264": {
    "nombre": "Pío",
    "apellido": "Torrent",
    "email": "higuerascharo@hotmail.com",
    "cue": [
      "1802397"
    ],
    "rol": "usuario",
    "login": "21270517264"
  },
  "29846447454": {
    "nombre": "Ciríaco",
    "apellido": "Sotelo",
    "email": "apuga@alvarez.es",
    "cue": [
      "1802558"
    ],
    "rol": "usuario",
    "login": "29846447454"
  },
  "28431385019": {
    "nombre": "Demetrio",
    "apellido": "Aroca",
    "email": "taniapizarro@vicens-marin.com",
    "cue": [
      "1805490"
    ],
    "rol": "usuario",
    "login": "28431385019"
  },
  "25436060089": {
    "nombre": "Martina",
    "apellido": "Palau",
    "email": "ratienza@urena.com",
    "cue": [
      "1808256"
    ],
    "rol": "usuario",
    "login": "25436060089"
  },
  "26790320882": {
    "nombre": "Amador",
    "apellido": "Maestre",
    "email": "pcortes@gmail.com",
    "cue": [
      "1802294"
    ],
    "rol": "usuario",
    "login": "26790320882"
  },
  "28464803340": {
    "nombre": "Rosendo",
    "apellido": "Duran",
    "email": "eladio20@yahoo.com",
    "cue": [
      "1804939"
    ],
    "rol": "usuario",
    "login": "28464803340"
  },
  "28292234804": {
    "nombre": "Azucena",
    "apellido": "Carlos",
    "email": "qiglesia@zamorano-pombo.es",
    "cue": [
      "1804075"
    ],
    "rol": "usuario",
    "login": "28292234804"
  },
  "24307412347": {
    "nombre": "Pilar",
    "apellido": "Acero",
    "email": "calvodomingo@contreras-mir.es",
    "cue": [
      "1801961"
    ],
    "rol": "usuario",
    "login": "24307412347"
  },
  "29072586119": {
    "nombre": "Beatriz",
    "apellido": "Benavides",
    "email": "concepcion79@gmail.com",
    "cue": [
      "1806488"
    ],
    "rol": "usuario",
    "login": "29072586119"
  },
  "24747905167": {
    "nombre": "Joaquín",
    "apellido": "Teruel",
    "email": "emelinagual@yahoo.com",
    "cue": [
      "1800312"
    ],
    "rol": "usuario",
    "login": "24747905167"
  },
  "23060295580": {
    "nombre": "Leoncio",
    "apellido": "Querol",
    "email": "wparejo@espejo.com",
    "cue": [
      "1800189"
    ],
    "rol": "usuario",
    "login": "23060295580"
  },
  "27318557787": {
    "nombre": "Paco",
    "apellido": "Carranza",
    "email": "aitor50@galan.com",
    "cue": [
      "1807783"
    ],
    "rol": "usuario",
    "login": "27318557787"
  },
  "27522059554": {
    "nombre": "Leandro",
    "apellido": "Tomé",
    "email": "adoraugarte@hotmail.com",
    "cue": [
      "1803664"
    ],
    "rol": "usuario",
    "login": "27522059554"
  }
}